nti/__init__.py
nti/i18n/__init__.py
nti/i18n/configure.zcml
nti/i18n/interfaces.py
nti/i18n/locales/__init__.py
nti/i18n/locales/cctld.py
nti/i18n/locales/configure.zcml
nti/i18n/locales/countries.json
nti/i18n/locales/countries.py
nti/i18n/locales/interfaces.py
nti/i18n/locales/tlds-alpha-by-domain.txt
nti/i18n/locales/tlds.json
nti/i18n/locales/tests/__init__.py
nti/i18n/locales/tests/test_cctld.py
nti/i18n/locales/tests/test_countries.py
nti/i18n/tests/__init__.py
nti/i18n/tests/test_interfaces.py
nti.i18n-1.1.0.post0.dist-info/LICENSE
nti.i18n-1.1.0.post0.dist-info/METADATA
nti.i18n-1.1.0.post0.dist-info/WHEEL
nti.i18n-1.1.0.post0.dist-info/top_level.txt
nti.i18n-1.1.0.post0.dist-info/zip-safe
nti.i18n-1.1.0.post0.dist-info/RECORD
