Metadata-Version: 2.1
Name: nti.i18n
Version: 1.1.0.post0
Summary: i18n and L10n data and interfaces
Home-page: https://github.com/OpenNTI/nti.i18n
Author: Jason Madden
Author-email: jason@nextthought.com
License: Apache
Keywords: i18n l10n zope component iana data locales
Classifier: Intended Audience :: Developers
Classifier: Natural Language :: English
Classifier: Operating System :: OS Independent
Classifier: License :: OSI Approved :: Apache Software License
Classifier: Programming Language :: Python :: 3 :: Only
Classifier: Programming Language :: Python :: 3.10
Classifier: Programming Language :: Python :: 3.11
Classifier: Programming Language :: Python :: 3.12
Classifier: Programming Language :: Python :: 3.13
Classifier: Programming Language :: Python :: Implementation :: CPython
Classifier: Programming Language :: Python :: Implementation :: PyPy
Classifier: Framework :: Zope3
Requires-Python: >= 3.10
License-File: LICENSE
Requires-Dist: zope.component
Requires-Dist: zope.interface
Requires-Dist: zope.cachedescriptors
Provides-Extra: docs
Requires-Dist: sphinx; extra == "docs"
Requires-Dist: sphinx-rtd-theme; extra == "docs"
Requires-Dist: repoze.sphinx.autointerface; extra == "docs"
Provides-Extra: plone
Requires-Dist: plone.i18n; extra == "plone"
Provides-Extra: test
Requires-Dist: zope.configuration; extra == "test"
Requires-Dist: zope.testrunner; extra == "test"
Requires-Dist: coverage; extra == "test"
